PythonEasyDB/__init__.py
PythonEasyDB/core.py
PythonEasyDB/utils.py
PythonEasyDB/engines/__init__.py
PythonEasyDB/engines/mongo_engine.py
PythonEasyDB/engines/postgres_engine.py
PythonEasyDB/engines/redis_engine.py
PythonEasyDB/engines/sqlite_engine.py
pythoneasydb-0.1.1.dist-info/licenses/LICENSE
tests/test_mongo_engine.py
tests/test_postgres_engine.py
tests/test_redis_engine.py
tests/test_sqlite.py
pythoneasydb-0.1.1.dist-info/METADATA
pythoneasydb-0.1.1.dist-info/WHEEL
pythoneasydb-0.1.1.dist-info/top_level.txt
pythoneasydb-0.1.1.dist-info/RECORD
