Metadata-Version: 2.4
Name: PythonEasyDB
Version: 0.1.1
Summary: Unified Python database client for SQLite, PostgreSQL, MongoDB, and Redis.
Home-page: https://github.com/asrorbekaliqulov/PythonEasyDB
Author: Asrorbek Aliqulov
Author-email: Asrorbek Aliqulov <asrorbekaliqulov08@gmail.com>
License: MIT
Project-URL: Homepage, https://github.com/asrorbekaliqulov/PythonEasyDB
Project-URL: Repository, https://github.com/asrorbekaliqulov/PythonEasyDB
Project-URL: Issues, https://github.com/asrorbekaliqulov/PythonEasyDB/issues
Requires-Python: >=3.7
License-File: LICENSE
Requires-Dist: psycopg2-binary>=2.9.0
Requires-Dist: pymongo>=4.0
Requires-Dist: redis>=5.0.0
Dynamic: author
Dynamic: home-page
Dynamic: license-file
Dynamic: requires-python
